[
  {
    "author": "ImangazalievM",
    "name": "android-developer-reference",
    "href": "https://github.com/ImangazalievM/android-developer-reference",
    "description": "🔥 A curated list of awesome Android articles sorted by topic.",
    "language": "Kotlin",
    "stars": 150,
    "forks": 7,
    "starsInPeriod": 18
  },
  {
    "author": "android",
    "name": "sunflower",
    "href": "https://github.com/android/sunflower",
    "description": "A gardening app illustrating Android development best practices with Android Jetpack.",
    "language": "Kotlin",
    "stars": 13144,
    "forks": 3133,
    "starsInPeriod": 13
  },
  {
    "author": "YTVanced",
    "name": "VancedManager",
    "href": "https://github.com/YTVanced/VancedManager",
    "description": "Vanced Installer",
    "language": "Kotlin",
    "stars": 2317,
    "forks": 132,
    "starsInPeriod": 16
  },
  {
    "author": "Shabinder",
    "name": "SpotiFlyer",
    "href": "https://github.com/Shabinder/SpotiFlyer",
    "description": "Spotify/Gaana/Youtube Music Downloader For Android!",
    "language": "Kotlin",
    "stars": 119,
    "forks": 15,
    "starsInPeriod": 6
  },
  {
    "author": "mozilla-mobile",
    "name": "fenix",
    "href": "https://github.com/mozilla-mobile/fenix",
    "description": "Firefox for Android",
    "language": "Kotlin",
    "stars": 4467,
    "forks": 674,
    "starsInPeriod": 8
  },
  {
    "author": "mockk",
    "name": "mockk",
    "href": "https://github.com/mockk/mockk",
    "description": "mocking library for Kotlin",
    "language": "Kotlin",
    "stars": 3591,
    "forks": 154,
    "starsInPeriod": 1
  },
  {
    "author": "kami-blue",
    "name": "client",
    "href": "https://github.com/kami-blue/client",
    "description": "KAMI Blue: a continuation of 1.12.2 KAMI",
    "language": "Kotlin",
    "stars": 207,
    "forks": 160,
    "starsInPeriod": 4
  },
  {
    "author": "android",
    "name": "compose-samples",
    "href": "https://github.com/android/compose-samples",
    "description": "Official Jetpack Compose samples.",
    "language": "Kotlin",
    "stars": 4614,
    "forks": 733,
    "starsInPeriod": 17
  },
  {
    "author": "pl3xgaming",
    "name": "Purpur",
    "href": "https://github.com/pl3xgaming/Purpur",
    "description": "Purpur is a fork of Paper and Tuinity with the goal of providing new and interesting configuration options, which allow for creating a unique gameplay experience not seen anywhere else",
    "language": "Kotlin",
    "stars": 145,
    "forks": 42,
    "starsInPeriod": 2
  },
  {
    "author": "alibaba",
    "name": "transmittable-thread-local",
    "href": "https://github.com/alibaba/transmittable-thread-local",
    "description": "📌 The missing Java™ std lib(simple & 0-dependency) for framework/middleware, provide an enhanced InheritableThreadLocal that transmits ThreadLocal values between threads even using thread pooling components.",
    "language": "Kotlin",
    "stars": 3427,
    "forks": 1027,
    "starsInPeriod": 1
  },
  {
    "author": "mozilla-mobile",
    "name": "android-components",
    "href": "https://github.com/mozilla-mobile/android-components",
    "description": "A collection of Android libraries to build browsers or browser-like applications.",
    "language": "Kotlin",
    "stars": 1628,
    "forks": 361,
    "starsInPeriod": 3
  },
  {
    "author": "mapbox",
    "name": "mapbox-navigation-android",
    "href": "https://github.com/mapbox/mapbox-navigation-android",
    "description": "Mapbox Navigation SDK for Android",
    "language": "Kotlin",
    "stars": 411,
    "forks": 255,
    "starsInPeriod": 2
  },
  {
    "author": "mamoe",
    "name": "mirai",
    "href": "https://github.com/mamoe/mirai",
    "description": "高效率 QQ 机器人框架 / High-performance bot framework for Tencent QQ",
    "language": "Kotlin",
    "stars": 4697,
    "forks": 1545,
    "starsInPeriod": 19
  },
  {
    "author": "zhaobozhen",
    "name": "LibChecker",
    "href": "https://github.com/zhaobozhen/LibChecker",
    "description": "An app to view libraries used in apps in your device.",
    "language": "Kotlin",
    "stars": 222,
    "forks": 23,
    "starsInPeriod": 4
  },
  {
    "author": "square",
    "name": "leakcanary",
    "href": "https://github.com/square/leakcanary",
    "description": "A memory leak detection library for Android.",
    "language": "Kotlin",
    "stars": 25629,
    "forks": 3708,
    "starsInPeriod": 4
  },
  {
    "author": "tipsy",
    "name": "javalin",
    "href": "https://github.com/tipsy/javalin",
    "description": "A simple and modern Java and Kotlin web framework",
    "language": "Kotlin",
    "stars": 4465,
    "forks": 394,
    "starsInPeriod": 6
  },
  {
    "author": "android",
    "name": "architecture-samples",
    "href": "https://github.com/android/architecture-samples",
    "description": "A collection of samples to discuss and showcase different architectural tools and patterns for Android apps.",
    "language": "Kotlin",
    "stars": 38005,
    "forks": 10502,
    "starsInPeriod": 14
  },
  {
    "author": "Kotlin",
    "name": "kotlinx.coroutines",
    "href": "https://github.com/Kotlin/kotlinx.coroutines",
    "description": "Library support for Kotlin coroutines",
    "language": "Kotlin",
    "stars": 8715,
    "forks": 1235,
    "starsInPeriod": 5
  },
  {
    "author": "Kotlin",
    "name": "kotlinx.serialization",
    "href": "https://github.com/Kotlin/kotlinx.serialization",
    "description": "Kotlin multiplatform / multi-format serialization",
    "language": "Kotlin",
    "stars": 2722,
    "forks": 292,
    "starsInPeriod": 5
  },
  {
    "author": "tachiyomiorg",
    "name": "tachiyomi",
    "href": "https://github.com/tachiyomiorg/tachiyomi",
    "description": "Free and open source manga reader for Android.",
    "language": "Kotlin",
    "stars": 9533,
    "forks": 1257,
    "starsInPeriod": 10
  },
  {
    "author": "hufman",
    "name": "AndroidAutoIdrive",
    "href": "https://github.com/hufman/AndroidAutoIdrive",
    "description": "Implementations of some Android Auto features as unofficial IDrive apps",
    "language": "Kotlin",
    "stars": 201,
    "forks": 46,
    "starsInPeriod": 2
  },
  {
    "author": "ExpediaGroup",
    "name": "graphql-kotlin",
    "href": "https://github.com/ExpediaGroup/graphql-kotlin",
    "description": "Libraries for running GraphQL in Kotlin",
    "language": "Kotlin",
    "stars": 942,
    "forks": 165,
    "starsInPeriod": 2
  },
  {
    "author": "detekt",
    "name": "detekt",
    "href": "https://github.com/detekt/detekt",
    "description": "Static code analysis for Kotlin",
    "language": "Kotlin",
    "stars": 3333,
    "forks": 437,
    "starsInPeriod": 1
  },
  {
    "author": "arkivanov",
    "name": "Decompose",
    "href": "https://github.com/arkivanov/Decompose",
    "description": "Kotlin Multiplatform lifecycle-aware business logic components (aka BLoCs) with routing functionality and pluggable UI (Jetpack Compose, SwiftUI, JS React, etc.)",
    "language": "Kotlin",
    "stars": 225,
    "forks": 8,
    "starsInPeriod": 6
  },
  {
    "author": "2dust",
    "name": "v2rayNG",
    "href": "https://github.com/2dust/v2rayNG",
    "description": null,
    "language": "Kotlin",
    "stars": 8182,
    "forks": 1595,
    "starsInPeriod": 16
  }
]