[{"author":"trimstray","name":"the-book-of-secret-knowledge","avatar":"https://github.com/trimstray.png","url":"https://github.com/trimstray/the-book-of-secret-knowledge","description":"A collection of inspiring lists, manuals, cheatsheets, blogs, hacks, one-liners, cli/web tools and more.","stars":27969,"forks":2836,"currentPeriodStars":333,"builtBy":[{"username":"trimstray","href":"https://github.com/trimstray","avatar":"https://avatars1.githubusercontent.com/u/31127917"},{"username":"lbonanomi","href":"https://github.com/lbonanomi","avatar":"https://avatars2.githubusercontent.com/u/5369016"},{"username":"loweryaustin","href":"https://github.com/loweryaustin","avatar":"https://avatars0.githubusercontent.com/u/2003860"},{"username":"the4rchangel","href":"https://github.com/the4rchangel","avatar":"https://avatars0.githubusercontent.com/u/32396866"},{"username":"KingOfDireWolves","href":"https://github.com/KingOfDireWolves","avatar":"https://avatars1.githubusercontent.com/u/22836245"}]},{"author":"microsoft","name":"playwright","avatar":"https://github.com/microsoft.png","url":"https://github.com/microsoft/playwright","description":"Node library to automate Chromium, Firefox and WebKit with a single API","language":"JavaScript","languageColor":"#f1e05a","stars":4868,"forks":86,"currentPeriodStars":2612,"builtBy":[{"username":"pavelfeldman","href":"https://github.com/pavelfeldman","avatar":"https://avatars1.githubusercontent.com/u/883973"},{"username":"dgozman","href":"https://github.com/dgozman","avatar":"https://avatars2.githubusercontent.com/u/9881434"},{"username":"aslushnikov","href":"https://github.com/aslushnikov","avatar":"https://avatars1.githubusercontent.com/u/746130"},{"username":"yury-s","href":"https://github.com/yury-s","avatar":"https://avatars0.githubusercontent.com/u/9798949"},{"username":"JoelEinbinder","href":"https://github.com/JoelEinbinder","avatar":"https://avatars3.githubusercontent.com/u/4624233"}]},{"author":"boston-dynamics","name":"spot-sdk","avatar":"https://github.com/boston-dynamics.png","url":"https://github.com/boston-dynamics/spot-sdk","description":"Spot SDK repo","language":"HTML","languageColor":"#e34c26","stars":257,"forks":31,"currentPeriodStars":112,"builtBy":[{"username":"bd-sdk-publisher","href":"https://github.com/bd-sdk-publisher","avatar":"https://avatars3.githubusercontent.com/u/53276189"}]},{"author":"fpereiro","name":"backendlore","avatar":"https://github.com/fpereiro.png","url":"https://github.com/fpereiro/backendlore","description":"How I write backends","stars":2579,"forks":104,"currentPeriodStars":704,"builtBy":[{"username":"fpereiro","href":"https://github.com/fpereiro","avatar":"https://avatars3.githubusercontent.com/u/1160018"},{"username":"sshine","href":"https://github.com/sshine","avatar":"https://avatars3.githubusercontent.com/u/50879"},{"username":"troydaniels","href":"https://github.com/troydaniels","avatar":"https://avatars0.githubusercontent.com/u/8019607"}]},{"author":"systemd","name":"systemd","avatar":"https://github.com/systemd.png","url":"https://github.com/systemd/systemd","description":"The systemd System and Service Manager","language":"C","languageColor":"#555555","stars":6013,"forks":1956,"currentPeriodStars":16,"builtBy":[{"username":"poettering","href":"https://github.com/poettering","avatar":"https://avatars3.githubusercontent.com/u/2130732"},{"username":"keszybz","href":"https://github.com/keszybz","avatar":"https://avatars1.githubusercontent.com/u/349618"},{"username":"kaysievers","href":"https://github.com/kaysievers","avatar":"https://avatars2.githubusercontent.com/u/1064936"},{"username":"yuwata","href":"https://github.com/yuwata","avatar":"https://avatars2.githubusercontent.com/u/14157143"},{"username":"teg","href":"https://github.com/teg","avatar":"https://avatars2.githubusercontent.com/u/5409"}]},{"author":"ErikCH","name":"DevYouTubeList","avatar":"https://github.com/ErikCH.png","url":"https://github.com/ErikCH/DevYouTubeList","description":"List of Development YouTube Channels","stars":1986,"forks":222,"currentPeriodStars":40,"builtBy":[{"username":"ErikCH","href":"https://github.com/ErikCH","avatar":"https://avatars1.githubusercontent.com/u/65630"},{"username":"MaheshPawar97","href":"https://github.com/MaheshPawar97","avatar":"https://avatars2.githubusercontent.com/u/32674489"},{"username":"karthickram286","href":"https://github.com/karthickram286","avatar":"https://avatars1.githubusercontent.com/u/23008268"},{"username":"Predaking2612","href":"https://github.com/Predaking2612","avatar":"https://avatars3.githubusercontent.com/u/33420975"},{"username":"codingride","href":"https://github.com/codingride","avatar":"https://avatars1.githubusercontent.com/u/7677815"}]},{"author":"specterops","name":"at-ps","avatar":"https://github.com/specterops.png","url":"https://github.com/specterops/at-ps","description":"Adversary Tactics - PowerShell Training","language":"PowerShell","languageColor":"#012456","stars":615,"forks":132,"currentPeriodStars":216,"builtBy":[{"username":"themightyshiv","href":"https://github.com/themightyshiv","avatar":"https://avatars2.githubusercontent.com/u/2651222"}]},{"author":"denoland","name":"deno","avatar":"https://github.com/denoland.png","url":"https://github.com/denoland/deno","description":"A secure JavaScript and TypeScript runtime","language":"TypeScript","languageColor":"#2b7489","stars":42483,"forks":1958,"currentPeriodStars":289,"builtBy":[{"username":"ry","href":"https://github.com/ry","avatar":"https://avatars2.githubusercontent.com/u/80"},{"username":"piscisaureus","href":"https://github.com/piscisaureus","avatar":"https://avatars1.githubusercontent.com/u/218257"},{"username":"bartlomieju","href":"https://github.com/bartlomieju","avatar":"https://avatars2.githubusercontent.com/u/13602871"},{"username":"kevinkassimo","href":"https://github.com/kevinkassimo","avatar":"https://avatars1.githubusercontent.com/u/15007517"},{"username":"kitsonk","href":"https://github.com/kitsonk","avatar":"https://avatars3.githubusercontent.com/u/1282577"}]},{"author":"public-apis","name":"public-apis","avatar":"https://github.com/public-apis.png","url":"https://github.com/public-apis/public-apis","description":"A collective list of free APIs for use in software and web development.","language":"Python","languageColor":"#3572A5","stars":69480,"forks":7847,"currentPeriodStars":114,"builtBy":[{"username":"davemachado","href":"https://github.com/davemachado","avatar":"https://avatars2.githubusercontent.com/u/15134885"},{"username":"mikestreety","href":"https://github.com/mikestreety","avatar":"https://avatars0.githubusercontent.com/u/354085"},{"username":"jbrooksuk","href":"https://github.com/jbrooksuk","avatar":"https://avatars0.githubusercontent.com/u/246103"},{"username":"toddmotto","href":"https://github.com/toddmotto","avatar":"https://avatars3.githubusercontent.com/u/1655968"},{"username":"wesbos","href":"https://github.com/wesbos","avatar":"https://avatars1.githubusercontent.com/u/176013"}]},{"author":"rasbt","name":"deeplearning-models","avatar":"https://github.com/rasbt.png","url":"https://github.com/rasbt/deeplearning-models","description":"A collection of various deep learning architectures, models, and tips","language":"Jupyter Notebook","languageColor":"#DA5B0B","stars":11334,"forks":2647,"currentPeriodStars":21,"builtBy":[{"username":"rasbt","href":"https://github.com/rasbt","avatar":"https://avatars1.githubusercontent.com/u/5618407"},{"username":"Vijayabhaskar96","href":"https://github.com/Vijayabhaskar96","avatar":"https://avatars2.githubusercontent.com/u/17958636"},{"username":"AdilZouitine","href":"https://github.com/AdilZouitine","avatar":"https://avatars0.githubusercontent.com/u/24889239"},{"username":"AlexZhou1995","href":"https://github.com/AlexZhou1995","avatar":"https://avatars1.githubusercontent.com/u/9313036"},{"username":"imatiach-msft","href":"https://github.com/imatiach-msft","avatar":"https://avatars3.githubusercontent.com/u/24683184"}]},{"author":"rasbt","name":"stat453-deep-learning-ss20","avatar":"https://github.com/rasbt.png","url":"https://github.com/rasbt/stat453-deep-learning-ss20","description":"STAT 453: Intro to Deep Learning @ UW-Madison (Spring 2020)","language":"TeX","languageColor":"#3D6117","stars":152,"forks":18,"currentPeriodStars":31,"builtBy":[{"username":"rasbt","href":"https://github.com/rasbt","avatar":"https://avatars1.githubusercontent.com/u/5618407"}]},{"author":"zeit","name":"next.js","avatar":"https://github.com/zeit.png","url":"https://github.com/zeit/next.js","description":"The React Framework","language":"JavaScript","languageColor":"#f1e05a","stars":44355,"forks":6147,"currentPeriodStars":33,"builtBy":[{"username":"timneutkens","href":"https://github.com/timneutkens","avatar":"https://avatars2.githubusercontent.com/u/6324199"},{"username":"Timer","href":"https://github.com/Timer","avatar":"https://avatars0.githubusercontent.com/u/616428"},{"username":"ijjk","href":"https://github.com/ijjk","avatar":"https://avatars3.githubusercontent.com/u/22380829"},{"username":"arunoda","href":"https://github.com/arunoda","avatar":"https://avatars3.githubusercontent.com/u/50838"},{"username":"nkzawa","href":"https://github.com/nkzawa","avatar":"https://avatars1.githubusercontent.com/u/775227"}]},{"author":"juliandavidmr","name":"awesome-nestjs","avatar":"https://github.com/juliandavidmr.png","url":"https://github.com/juliandavidmr/awesome-nestjs","description":"😏 Curated list of NestJS","stars":1939,"forks":195,"currentPeriodStars":5,"builtBy":[{"username":"juliandavidmr","href":"https://github.com/juliandavidmr","avatar":"https://avatars3.githubusercontent.com/u/4544102"},{"username":"bashleigh","href":"https://github.com/bashleigh","avatar":"https://avatars3.githubusercontent.com/u/11574250"},{"username":"nartc","href":"https://github.com/nartc","avatar":"https://avatars3.githubusercontent.com/u/25516557"},{"username":"fenos","href":"https://github.com/fenos","avatar":"https://avatars3.githubusercontent.com/u/4754064"},{"username":"iamolegga","href":"https://github.com/iamolegga","avatar":"https://avatars3.githubusercontent.com/u/5501657"}]},{"author":"anvaka","name":"city-roads","avatar":"https://github.com/anvaka.png","url":"https://github.com/anvaka/city-roads","description":"Visualization of all roads within any city","language":"JavaScript","languageColor":"#f1e05a","stars":1628,"forks":91,"currentPeriodStars":350,"builtBy":[{"username":"anvaka","href":"https://github.com/anvaka","avatar":"https://avatars2.githubusercontent.com/u/225407"}]},{"author":"quarkusio","name":"quarkus","avatar":"https://github.com/quarkusio.png","url":"https://github.com/quarkusio/quarkus","description":"Quarkus: Supersonic Subatomic Java.","language":"Java","languageColor":"#b07219","stars":3798,"forks":638,"currentPeriodStars":10,"builtBy":[{"username":"gsmet","href":"https://github.com/gsmet","avatar":"https://avatars3.githubusercontent.com/u/1279749"},{"username":"stuartwdouglas","href":"https://github.com/stuartwdouglas","avatar":"https://avatars3.githubusercontent.com/u/328571"},{"username":"cescoffier","href":"https://github.com/cescoffier","avatar":"https://avatars1.githubusercontent.com/u/402301"},{"username":"geoand","href":"https://github.com/geoand","avatar":"https://avatars2.githubusercontent.com/u/4374975"},{"username":"Sanne","href":"https://github.com/Sanne","avatar":"https://avatars1.githubusercontent.com/u/42573"}]},{"author":"angular","name":"angular-cli","avatar":"https://github.com/angular.png","url":"https://github.com/angular/angular-cli","description":"CLI tool for Angular","language":"TypeScript","languageColor":"#2b7489","stars":22914,"forks":8321,"currentPeriodStars":10,"builtBy":[{"username":"filipesilva","href":"https://github.com/filipesilva","avatar":"https://avatars1.githubusercontent.com/u/4172079"},{"username":"clydin","href":"https://github.com/clydin","avatar":"https://avatars3.githubusercontent.com/u/19598772"},{"username":"hansl","href":"https://github.com/hansl","avatar":"https://avatars2.githubusercontent.com/u/681969"},{"username":"renovate-bot","href":"https://github.com/renovate-bot","avatar":"https://avatars1.githubusercontent.com/u/25180681"},{"username":"Brocco","href":"https://github.com/Brocco","avatar":"https://avatars1.githubusercontent.com/u/1565117"}]},{"author":"MunGell","name":"awesome-for-beginners","avatar":"https://github.com/MunGell.png","url":"https://github.com/MunGell/awesome-for-beginners","description":"A list of awesome beginners-friendly projects.","stars":15910,"forks":2653,"currentPeriodStars":33,"builtBy":[{"username":"MunGell","href":"https://github.com/MunGell","avatar":"https://avatars0.githubusercontent.com/u/812976"},{"username":"JefMari","href":"https://github.com/JefMari","avatar":"https://avatars1.githubusercontent.com/u/12628112"},{"username":"abhi18av","href":"https://github.com/abhi18av","avatar":"https://avatars1.githubusercontent.com/u/12799326"},{"username":"nedbat","href":"https://github.com/nedbat","avatar":"https://avatars2.githubusercontent.com/u/23789"},{"username":"CodeTheory","href":"https://github.com/CodeTheory","avatar":"https://avatars1.githubusercontent.com/u/48335493"}]},{"author":"TheAlgorithms","name":"Javascript","avatar":"https://github.com/TheAlgorithms.png","url":"https://github.com/TheAlgorithms/Javascript","description":"A repository for All algorithms implemented in Javascript (for educational purposes only)","language":"JavaScript","languageColor":"#f1e05a","stars":1669,"forks":396,"currentPeriodStars":14,"builtBy":[{"username":"ms10398","href":"https://github.com/ms10398","avatar":"https://avatars1.githubusercontent.com/u/26259547"},{"username":"christianbender","href":"https://github.com/christianbender","avatar":"https://avatars0.githubusercontent.com/u/23243382"},{"username":"winsonrich","href":"https://github.com/winsonrich","avatar":"https://avatars2.githubusercontent.com/u/42903383"},{"username":"AnupKumarPanwar","href":"https://github.com/AnupKumarPanwar","avatar":"https://avatars2.githubusercontent.com/u/10573038"},{"username":"PatOnTheBack","href":"https://github.com/PatOnTheBack","avatar":"https://avatars3.githubusercontent.com/u/51241310"}]},{"author":"terraform-providers","name":"terraform-provider-aws","avatar":"https://github.com/terraform-providers.png","url":"https://github.com/terraform-providers/terraform-provider-aws","description":"Terraform AWS provider","language":"Go","languageColor":"#00ADD8","stars":3620,"forks":3326,"currentPeriodStars":4,"builtBy":[{"username":"bflad","href":"https://github.com/bflad","avatar":"https://avatars0.githubusercontent.com/u/189114"},{"username":"radeksimko","href":"https://github.com/radeksimko","avatar":"https://avatars3.githubusercontent.com/u/287584"},{"username":"catsby","href":"https://github.com/catsby","avatar":"https://avatars2.githubusercontent.com/u/61721"},{"username":"stack72","href":"https://github.com/stack72","avatar":"https://avatars3.githubusercontent.com/u/227823"},{"username":"ryndaniels","href":"https://github.com/ryndaniels","avatar":"https://avatars1.githubusercontent.com/u/397565"}]},{"author":"sehno","name":"Bug-bounty","avatar":"https://github.com/sehno.png","url":"https://github.com/sehno/Bug-bounty","description":"Ressources for bug bounty hunting","stars":90,"forks":40,"currentPeriodStars":20,"builtBy":[{"username":"sehno","href":"https://github.com/sehno","avatar":"https://avatars2.githubusercontent.com/u/25466815"}]},{"author":"dank","name":"tarkov","avatar":"https://github.com/dank.png","url":"https://github.com/dank/tarkov","description":"A Rust library for the Escape from Tarkov API","language":"Rust","languageColor":"#dea584","stars":22,"forks":8,"currentPeriodStars":4,"builtBy":[{"username":"dank","href":"https://github.com/dank","avatar":"https://avatars2.githubusercontent.com/u/1585101"}]},{"author":"streamlit","name":"streamlit","avatar":"https://github.com/streamlit.png","url":"https://github.com/streamlit/streamlit","description":"Streamlit — The fastest way to build custom ML tools","language":"Python","languageColor":"#3572A5","stars":6546,"forks":563,"currentPeriodStars":24,"builtBy":[{"username":"tvst","href":"https://github.com/tvst","avatar":"https://avatars1.githubusercontent.com/u/690814"},{"username":"treuille","href":"https://github.com/treuille","avatar":"https://avatars2.githubusercontent.com/u/1673013"},{"username":"aaj-st","href":"https://github.com/aaj-st","avatar":"https://avatars0.githubusercontent.com/u/44782696"},{"username":"tconkling","href":"https://github.com/tconkling","avatar":"https://avatars1.githubusercontent.com/u/709022"},{"username":"kantuni","href":"https://github.com/kantuni","avatar":"https://avatars1.githubusercontent.com/u/6151409"}]},{"author":"awesomedata","name":"awesome-public-datasets","avatar":"https://github.com/awesomedata.png","url":"https://github.com/awesomedata/awesome-public-datasets","description":"A topic-centric list of HQ open datasets. PR ☛☛☛","stars":37326,"forks":6482,"currentPeriodStars":37,"builtBy":[{"username":"caesar0301","href":"https://github.com/caesar0301","avatar":"https://avatars3.githubusercontent.com/u/499254"},{"username":"ReadmeCritic","href":"https://github.com/ReadmeCritic","avatar":"https://avatars3.githubusercontent.com/u/15367484"},{"username":"alexurquhart","href":"https://github.com/alexurquhart","avatar":"https://avatars1.githubusercontent.com/u/3111563"},{"username":"franc00018","href":"https://github.com/franc00018","avatar":"https://avatars3.githubusercontent.com/u/5459276"},{"username":"phillc73","href":"https://github.com/phillc73","avatar":"https://avatars0.githubusercontent.com/u/815126"}]},{"author":"99designs","name":"gqlgen","avatar":"https://github.com/99designs.png","url":"https://github.com/99designs/gqlgen","description":"go generate based graphql server library","language":"Go","languageColor":"#00ADD8","stars":3846,"forks":362,"currentPeriodStars":9,"builtBy":[{"username":"vektah","href":"https://github.com/vektah","avatar":"https://avatars0.githubusercontent.com/u/2247982"},{"username":"neelance","href":"https://github.com/neelance","avatar":"https://avatars2.githubusercontent.com/u/16184"},{"username":"mathewbyrne","href":"https://github.com/mathewbyrne","avatar":"https://avatars0.githubusercontent.com/u/23903"},{"username":"vvakame","href":"https://github.com/vvakame","avatar":"https://avatars1.githubusercontent.com/u/125332"},{"username":"hantonelli","href":"https://github.com/hantonelli","avatar":"https://avatars2.githubusercontent.com/u/18269845"}]},{"author":"jiahaog","name":"nativefier","avatar":"https://github.com/jiahaog.png","url":"https://github.com/jiahaog/nativefier","description":"Make any web page a desktop application","language":"JavaScript","languageColor":"#f1e05a","stars":22010,"forks":1343,"currentPeriodStars":18,"builtBy":[{"username":"jiahaog","href":"https://github.com/jiahaog","avatar":"https://avatars1.githubusercontent.com/u/7111741"},{"username":"maxogden","href":"https://github.com/maxogden","avatar":"https://avatars1.githubusercontent.com/u/39759"},{"username":"ronjouch","href":"https://github.com/ronjouch","avatar":"https://avatars3.githubusercontent.com/u/522085"},{"username":"bacongravy","href":"https://github.com/bacongravy","avatar":"https://avatars3.githubusercontent.com/u/16848768"},{"username":"zweicoder","href":"https://github.com/zweicoder","avatar":"https://avatars2.githubusercontent.com/u/3684550"}]}]