[
  {
    "author": "artichoke",
    "name": "artichoke",
    "href": "https://github.com/artichoke/artichoke",
    "description": "💎 Artichoke is a Ruby made with Rust",
    "language": "Rust",
    "stars": 2006,
    "forks": 68,
    "starsInPeriod": 315
  },
  {
    "author": "nushell",
    "name": "nushell",
    "href": "https://github.com/nushell/nushell",
    "description": "A new type of shell",
    "language": "Rust",
    "stars": 9027,
    "forks": 474,
    "starsInPeriod": 37
  },
  {
    "author": "ruffle-rs",
    "name": "ruffle",
    "href": "https://github.com/ruffle-rs/ruffle",
    "description": "A Flash Player emulator written in Rust",
    "language": "Rust",
    "stars": 5817,
    "forks": 193,
    "starsInPeriod": 160
  },
  {
    "author": "seanmonstar",
    "name": "reqwest",
    "href": "https://github.com/seanmonstar/reqwest",
    "description": "An easy and powerful Rust HTTP Client",
    "language": "Rust",
    "stars": 3479,
    "forks": 454,
    "starsInPeriod": 14
  },
  {
    "author": "rust-lang",
    "name": "book",
    "href": "https://github.com/rust-lang/book",
    "description": "The Rust Programming Language",
    "language": "Rust",
    "stars": 6256,
    "forks": 1685,
    "starsInPeriod": 11
  },
  {
    "author": "rust-lang",
    "name": "mdBook",
    "href": "https://github.com/rust-lang/mdBook",
    "description": "Create book from markdown files. Like Gitbook but implemented in Rust",
    "language": "Rust",
    "stars": 5562,
    "forks": 646,
    "starsInPeriod": 17
  },
  {
    "author": "rust-lang",
    "name": "rustlings",
    "href": "https://github.com/rust-lang/rustlings",
    "description": "🦀 Small exercises to get you used to reading and writing Rust code!",
    "language": "Rust",
    "stars": 13624,
    "forks": 1727,
    "starsInPeriod": 64
  },
  {
    "author": "linebender",
    "name": "druid",
    "href": "https://github.com/linebender/druid",
    "description": "A data-first Rust-native UI design toolkit.",
    "language": "Rust",
    "stars": 2975,
    "forks": 244,
    "starsInPeriod": 53
  },
  {
    "author": "rust-unofficial",
    "name": "awesome-rust",
    "href": "https://github.com/rust-unofficial/awesome-rust",
    "description": "A curated list of Rust code and resources.",
    "language": "Rust",
    "stars": 18079,
    "forks": 1231,
    "starsInPeriod": 32
  },
  {
    "author": "starship",
    "name": "starship",
    "href": "https://github.com/starship/starship",
    "description": "☄🌌️ The minimal, blazing-fast, and infinitely customizable prompt for any shell!",
    "language": "Rust",
    "stars": 13332,
    "forks": 559,
    "starsInPeriod": 32
  },
  {
    "author": "diem",
    "name": "diem",
    "href": "https://github.com/diem/diem",
    "description": "Diem’s mission is to enable a simple global payment system and financial infrastructure that empowers billions of people.",
    "language": "Rust",
    "stars": 15549,
    "forks": 2365,
    "starsInPeriod": 16
  },
  {
    "author": "diesel-rs",
    "name": "diesel",
    "href": "https://github.com/diesel-rs/diesel",
    "description": "A safe, extensible ORM and Query Builder for Rust",
    "language": "Rust",
    "stars": 6302,
    "forks": 611,
    "starsInPeriod": 14
  },
  {
    "author": "rustwasm",
    "name": "wasm-bindgen",
    "href": "https://github.com/rustwasm/wasm-bindgen",
    "description": "Facilitating high-level interactions between Wasm modules and JavaScript",
    "language": "Rust",
    "stars": 3811,
    "forks": 520,
    "starsInPeriod": 9
  },
  {
    "author": "tikv",
    "name": "tikv",
    "href": "https://github.com/tikv/tikv",
    "description": "Distributed transactional key-value database, originally created to complement TiDB",
    "language": "Rust",
    "stars": 8565,
    "forks": 1332,
    "starsInPeriod": 10
  },
  {
    "author": "rust-lang",
    "name": "rust-clippy",
    "href": "https://github.com/rust-lang/rust-clippy",
    "description": "A bunch of lints to catch common mistakes and improve your Rust code",
    "language": "Rust",
    "stars": 5348,
    "forks": 746,
    "starsInPeriod": 18
  },
  {
    "author": "launchbadge",
    "name": "sqlx",
    "href": "https://github.com/launchbadge/sqlx",
    "description": "🧰 The Rust SQL Toolkit. An async, pure Rust SQL crate featuring compile-time checked queries without a DSL. Supports PostgreSQL, MySQL, SQLite, and MSSQL.",
    "language": "Rust",
    "stars": 3203,
    "forks": 283,
    "starsInPeriod": 14
  },
  {
    "author": "ogham",
    "name": "exa",
    "href": "https://github.com/ogham/exa",
    "description": "A modern replacement for ‘ls’.",
    "language": "Rust",
    "stars": 11807,
    "forks": 358,
    "starsInPeriod": 178
  },
  {
    "author": "getzola",
    "name": "zola",
    "href": "https://github.com/getzola/zola",
    "description": "A fast static site generator in a single binary with everything built-in. https://www.getzola.org",
    "language": "Rust",
    "stars": 4745,
    "forks": 404,
    "starsInPeriod": 25
  },
  {
    "author": "PyO3",
    "name": "pyo3",
    "href": "https://github.com/PyO3/pyo3",
    "description": "Rust bindings for the Python interpreter",
    "language": "Rust",
    "stars": 3295,
    "forks": 223,
    "starsInPeriod": 10
  },
  {
    "author": "alacritty",
    "name": "alacritty",
    "href": "https://github.com/alacritty/alacritty",
    "description": "A cross-platform, OpenGL terminal emulator.",
    "language": "Rust",
    "stars": 28962,
    "forks": 1480,
    "starsInPeriod": 52
  },
  {
    "author": "paritytech",
    "name": "polkadot",
    "href": "https://github.com/paritytech/polkadot",
    "description": "Polkadot Node Implementation",
    "language": "Rust",
    "stars": 1922,
    "forks": 445,
    "starsInPeriod": 27
  },
  {
    "author": "hecrj",
    "name": "iced",
    "href": "https://github.com/hecrj/iced",
    "description": "A cross-platform GUI library for Rust, inspired by Elm",
    "language": "Rust",
    "stars": 8139,
    "forks": 337,
    "starsInPeriod": 24
  },
  {
    "author": "librespot-org",
    "name": "librespot",
    "href": "https://github.com/librespot-org/librespot",
    "description": "Open Source Spotify client library",
    "language": "Rust",
    "stars": 1891,
    "forks": 255,
    "starsInPeriod": 9
  },
  {
    "author": "seanmonstar",
    "name": "warp",
    "href": "https://github.com/seanmonstar/warp",
    "description": "A super-easy, composable, web server framework for warp speeds.",
    "language": "Rust",
    "stars": 3751,
    "forks": 377,
    "starsInPeriod": 12
  },
  {
    "author": "actix",
    "name": "actix",
    "href": "https://github.com/actix/actix",
    "description": "Actor framework for Rust.",
    "language": "Rust",
    "stars": 5878,
    "forks": 514,
    "starsInPeriod": 10
  }
]